deciphon_sched/__init__.py
deciphon_sched/cli.py
deciphon_sched/database.py
deciphon_sched/errors.py
deciphon_sched/journal.py
deciphon_sched/logger.py
deciphon_sched/main.py
deciphon_sched/settings.py
deciphon_sched/signals.py
deciphon_sched/storage.py
deciphon_sched/testing.py
deciphon_sched/url.py
deciphon_sched/sched/__init__.py
deciphon_sched/sched/dbs.py
deciphon_sched/sched/health.py
deciphon_sched/sched/hmms.py
deciphon_sched/sched/jobs.py
deciphon_sched/sched/models.py
deciphon_sched/sched/scans.py
deciphon_sched/sched/schemas.py
deciphon_sched/sched/seqs.py
deciphon_sched-1.2.2.dist-info/METADATA
deciphon_sched-1.2.2.dist-info/WHEEL
deciphon_sched-1.2.2.dist-info/entry_points.txt
deciphon_sched-1.2.2.dist-info/licenses/LICENSE
deciphon_sched-1.2.2.dist-info/RECORD
